[
    {
        "id": "0",
        "name": "rhombus",
        "region": {
            "origin": {
                "x": "42",
                "y": "173"
            },
            "size": {
                "width": "33",
                "height": "33"
            }
        }
    },
    {
        "id": "1",
        "name": "rhombus",
        "region": {
            "origin": {
                "x": "194",
                "y": "97"
            },
            "size": {
                "width": "27",
                "height": "27"
            }
        }
    }
]