[
    {
        "id": "0",
        "name": "circle",
        "region": {
            "origin": {
                "x": "174",
                "y": "149"
            },
            "size": {
                "width": "30",
                "height": "30"
            }
        }
    },
    {
        "id": "1",
        "name": "rhombus",
        "region": {
            "origin": {
                "x": "19",
                "y": "125"
            },
            "size": {
                "width": "34",
                "height": "34"
            }
        }
    }
]