[
    {
        "id": "0",
        "name": "hexagon",
        "region": {
            "origin": {
                "x": "53",
                "y": "135"
            },
            "size": {
                "width": "33",
                "height": "37"
            }
        }
    },
    {
        "id": "1",
        "name": "rhombus",
        "region": {
            "origin": {
                "x": "180",
                "y": "167"
            },
            "size": {
                "width": "37",
                "height": "37"
            }
        }
    },
    {
        "id": "2",
        "name": "rhombus",
        "region": {
            "origin": {
                "x": "73",
                "y": "74"
            },
            "size": {
                "width": "33",
                "height": "33"
            }
        }
    },
    {
        "id": "3",
        "name": "triangle",
        "region": {
            "origin": {
                "x": "193",
                "y": "56"
            },
            "size": {
                "width": "33",
                "height": "26"
            }
        }
    },
    {
        "id": "4",
        "name": "rhombus",
        "region": {
            "origin": {
                "x": "124",
                "y": "107"
            },
            "size": {
                "width": "21",
                "height": "21"
            }
        }
    }
]