[
    {
        "id": "0",
        "name": "circle",
        "region": {
            "origin": {
                "x": "170",
                "y": "55"
            },
            "size": {
                "width": "30",
                "height": "30"
            }
        }
    },
    {
        "id": "1",
        "name": "rhombus",
        "region": {
            "origin": {
                "x": "41",
                "y": "191"
            },
            "size": {
                "width": "29",
                "height": "29"
            }
        }
    },
    {
        "id": "2",
        "name": "triangle",
        "region": {
            "origin": {
                "x": "91",
                "y": "52"
            },
            "size": {
                "width": "28",
                "height": "27"
            }
        }
    },
    {
        "id": "3",
        "name": "rhombus",
        "region": {
            "origin": {
                "x": "178",
                "y": "159"
            },
            "size": {
                "width": "24",
                "height": "24"
            }
        }
    },
    {
        "id": "4",
        "name": "circle",
        "region": {
            "origin": {
                "x": "114",
                "y": "117"
            },
            "size": {
                "width": "30",
                "height": "30"
            }
        }
    }
]