[
    {
        "id": "0",
        "name": "circle",
        "region": {
            "origin": {
                "x": "170",
                "y": "198"
            },
            "size": {
                "width": "30",
                "height": "30"
            }
        }
    },
    {
        "id": "1",
        "name": "hexagon",
        "region": {
            "origin": {
                "x": "174",
                "y": "53"
            },
            "size": {
                "width": "38",
                "height": "40"
            }
        }
    },
    {
        "id": "2",
        "name": "hexagon",
        "region": {
            "origin": {
                "x": "3",
                "y": "124"
            },
            "size": {
                "width": "36",
                "height": "42"
            }
        }
    },
    {
        "id": "3",
        "name": "circle",
        "region": {
            "origin": {
                "x": "73",
                "y": "27"
            },
            "size": {
                "width": "30",
                "height": "30"
            }
        }
    },
    {
        "id": "4",
        "name": "hexagon",
        "region": {
            "origin": {
                "x": "94",
                "y": "102"
            },
            "size": {
                "width": "29",
                "height": "32"
            }
        }
    }
]