[
    {
        "id": "0",
        "name": "hexagon",
        "region": {
            "origin": {
                "x": "20",
                "y": "140"
            },
            "size": {
                "width": "29",
                "height": "35"
            }
        }
    },
    {
        "id": "1",
        "name": "circle",
        "region": {
            "origin": {
                "x": "54",
                "y": "24"
            },
            "size": {
                "width": "30",
                "height": "30"
            }
        }
    },
    {
        "id": "2",
        "name": "hexagon",
        "region": {
            "origin": {
                "x": "192",
                "y": "52"
            },
            "size": {
                "width": "37",
                "height": "41"
            }
        }
    },
    {
        "id": "3",
        "name": "rhombus",
        "region": {
            "origin": {
                "x": "165",
                "y": "178"
            },
            "size": {
                "width": "30",
                "height": "30"
            }
        }
    },
    {
        "id": "4",
        "name": "circle",
        "region": {
            "origin": {
                "x": "115",
                "y": "121"
            },
            "size": {
                "width": "30",
                "height": "30"
            }
        }
    }
]