[
    {
        "id": "0",
        "name": "hexagon",
        "region": {
            "origin": {
                "x": "149",
                "y": "159"
            },
            "size": {
                "width": "35",
                "height": "39"
            }
        }
    },
    {
        "id": "1",
        "name": "triangle",
        "region": {
            "origin": {
                "x": "91",
                "y": "23"
            },
            "size": {
                "width": "31",
                "height": "39"
            }
        }
    }
]