[
    {
        "id": "0",
        "name": "hexagon",
        "region": {
            "origin": {
                "x": "170",
                "y": "187"
            },
            "size": {
                "width": "32",
                "height": "32"
            }
        }
    },
    {
        "id": "1",
        "name": "circle",
        "region": {
            "origin": {
                "x": "62",
                "y": "46"
            },
            "size": {
                "width": "34",
                "height": "34"
            }
        }
    },
    {
        "id": "2",
        "name": "circle",
        "region": {
            "origin": {
                "x": "47",
                "y": "187"
            },
            "size": {
                "width": "34",
                "height": "34"
            }
        }
    },
    {
        "id": "3",
        "name": "triangle",
        "region": {
            "origin": {
                "x": "191",
                "y": "65"
            },
            "size": {
                "width": "30",
                "height": "28"
            }
        }
    },
    {
        "id": "4",
        "name": "rhombus",
        "region": {
            "origin": {
                "x": "127",
                "y": "113"
            },
            "size": {
                "width": "35",
                "height": "35"
            }
        }
    }
]