[
    {
        "id": "0",
        "name": "hexagon",
        "region": {
            "origin": {
                "x": "180",
                "y": "39"
            },
            "size": {
                "width": "34",
                "height": "34"
            }
        }
    },
    {
        "id": "1",
        "name": "circle",
        "region": {
            "origin": {
                "x": "75",
                "y": "179"
            },
            "size": {
                "width": "34",
                "height": "34"
            }
        }
    },
    {
        "id": "2",
        "name": "hexagon",
        "region": {
            "origin": {
                "x": "60",
                "y": "59"
            },
            "size": {
                "width": "28",
                "height": "33"
            }
        }
    },
    {
        "id": "3",
        "name": "circle",
        "region": {
            "origin": {
                "x": "170",
                "y": "197"
            },
            "size": {
                "width": "34",
                "height": "34"
            }
        }
    }
]