[
    {
        "id": "0",
        "name": "hexagon",
        "region": {
            "origin": {
                "x": "61",
                "y": "34"
            },
            "size": {
                "width": "35",
                "height": "39"
            }
        }
    },
    {
        "id": "1",
        "name": "rhombus",
        "region": {
            "origin": {
                "x": "198",
                "y": "69"
            },
            "size": {
                "width": "31",
                "height": "31"
            }
        }
    },
    {
        "id": "2",
        "name": "hexagon",
        "region": {
            "origin": {
                "x": "41",
                "y": "139"
            },
            "size": {
                "width": "38",
                "height": "39"
            }
        }
    }
]