[
    {
        "id": "0",
        "name": "hexagon",
        "region": {
            "origin": {
                "x": "177",
                "y": "50"
            },
            "size": {
                "width": "30",
                "height": "30"
            }
        }
    },
    {
        "id": "1",
        "name": "hexagon",
        "region": {
            "origin": {
                "x": "47",
                "y": "55"
            },
            "size": {
                "width": "36",
                "height": "36"
            }
        }
    },
    {
        "id": "2",
        "name": "hexagon",
        "region": {
            "origin": {
                "x": "178",
                "y": "169"
            },
            "size": {
                "width": "34",
                "height": "40"
            }
        }
    },
    {
        "id": "3",
        "name": "triangle",
        "region": {
            "origin": {
                "x": "71",
                "y": "182"
            },
            "size": {
                "width": "29",
                "height": "42"
            }
        }
    }
]