[
    {
        "id": "0",
        "name": "hexagon",
        "region": {
            "origin": {
                "x": "72",
                "y": "51"
            },
            "size": {
                "width": "30",
                "height": "30"
            }
        }
    },
    {
        "id": "1",
        "name": "circle",
        "region": {
            "origin": {
                "x": "157",
                "y": "166"
            },
            "size": {
                "width": "34",
                "height": "34"
            }
        }
    },
    {
        "id": "2",
        "name": "triangle",
        "region": {
            "origin": {
                "x": "70",
                "y": "173"
            },
            "size": {
                "width": "31",
                "height": "37"
            }
        }
    }
]