[
    {
        "id": "0",
        "name": "hexagon",
        "region": {
            "origin": {
                "x": "139",
                "y": "159"
            },
            "size": {
                "width": "34",
                "height": "42"
            }
        }
    },
    {
        "id": "1",
        "name": "circle",
        "region": {
            "origin": {
                "x": "53",
                "y": "40"
            },
            "size": {
                "width": "34",
                "height": "34"
            }
        }
    },
    {
        "id": "2",
        "name": "hexagon",
        "region": {
            "origin": {
                "x": "62",
                "y": "140"
            },
            "size": {
                "width": "38",
                "height": "39"
            }
        }
    },
    {
        "id": "3",
        "name": "circle",
        "region": {
            "origin": {
                "x": "152",
                "y": "49"
            },
            "size": {
                "width": "34",
                "height": "34"
            }
        }
    },
    {
        "id": "4",
        "name": "circle",
        "region": {
            "origin": {
                "x": "120",
                "y": "98"
            },
            "size": {
                "width": "34",
                "height": "34"
            }
        }
    }
]