[
    {
        "id": "0",
        "name": "hexagon",
        "region": {
            "origin": {
                "x": "141",
                "y": "164"
            },
            "size": {
                "width": "36",
                "height": "38"
            }
        }
    },
    {
        "id": "1",
        "name": "hexagon",
        "region": {
            "origin": {
                "x": "16",
                "y": "138"
            },
            "size": {
                "width": "29",
                "height": "33"
            }
        }
    },
    {
        "id": "2",
        "name": "triangle",
        "region": {
            "origin": {
                "x": "79",
                "y": "14"
            },
            "size": {
                "width": "30",
                "height": "41"
            }
        }
    },
    {
        "id": "3",
        "name": "triangle",
        "region": {
            "origin": {
                "x": "186",
                "y": "48"
            },
            "size": {
                "width": "29",
                "height": "41"
            }
        }
    }
]