[
    {
        "id": "0",
        "name": "hexagon",
        "region": {
            "origin": {
                "x": "167",
                "y": "159"
            },
            "size": {
                "width": "29",
                "height": "35"
            }
        }
    },
    {
        "id": "1",
        "name": "rhombus",
        "region": {
            "origin": {
                "x": "204",
                "y": "96"
            },
            "size": {
                "width": "34",
                "height": "34"
            }
        }
    }
]