[
    {
        "id": "0",
        "name": "hexagon",
        "region": {
            "origin": {
                "x": "157",
                "y": "68"
            },
            "size": {
                "width": "30",
                "height": "30"
            }
        }
    },
    {
        "id": "1",
        "name": "hexagon",
        "region": {
            "origin": {
                "x": "65",
                "y": "144"
            },
            "size": {
                "width": "30",
                "height": "31"
            }
        }
    },
    {
        "id": "2",
        "name": "triangle",
        "region": {
            "origin": {
                "x": "66",
                "y": "55"
            },
            "size": {
                "width": "34",
                "height": "25"
            }
        }
    }
]