[
    {
        "id": "0",
        "name": "hexagon",
        "region": {
            "origin": {
                "x": "56",
                "y": "163"
            },
            "size": {
                "width": "33",
                "height": "37"
            }
        }
    },
    {
        "id": "1",
        "name": "rhombus",
        "region": {
            "origin": {
                "x": "179",
                "y": "57"
            },
            "size": {
                "width": "21",
                "height": "21"
            }
        }
    },
    {
        "id": "2",
        "name": "circle",
        "region": {
            "origin": {
                "x": "169",
                "y": "178"
            },
            "size": {
                "width": "30",
                "height": "30"
            }
        }
    }
]