[
    {
        "id": "0",
        "name": "hexagon",
        "region": {
            "origin": {
                "x": "182",
                "y": "160"
            },
            "size": {
                "width": "28",
                "height": "33"
            }
        }
    },
    {
        "id": "1",
        "name": "circle",
        "region": {
            "origin": {
                "x": "164",
                "y": "75"
            },
            "size": {
                "width": "34",
                "height": "34"
            }
        }
    },
    {
        "id": "2",
        "name": "rhombus",
        "region": {
            "origin": {
                "x": "65",
                "y": "156"
            },
            "size": {
                "width": "22",
                "height": "22"
            }
        }
    }
]