[
    {
        "id": "0",
        "name": "hexagon",
        "region": {
            "origin": {
                "x": "166",
                "y": "158"
            },
            "size": {
                "width": "38",
                "height": "39"
            }
        }
    },
    {
        "id": "1",
        "name": "hexagon",
        "region": {
            "origin": {
                "x": "52",
                "y": "31"
            },
            "size": {
                "width": "30",
                "height": "31"
            }
        }
    },
    {
        "id": "2",
        "name": "circle",
        "region": {
            "origin": {
                "x": "154",
                "y": "23"
            },
            "size": {
                "width": "34",
                "height": "34"
            }
        }
    },
    {
        "id": "3",
        "name": "rhombus",
        "region": {
            "origin": {
                "x": "37",
                "y": "137"
            },
            "size": {
                "width": "29",
                "height": "29"
            }
        }
    },
    {
        "id": "4",
        "name": "triangle",
        "region": {
            "origin": {
                "x": "120",
                "y": "116"
            },
            "size": {
                "width": "30",
                "height": "49"
            }
        }
    }
]