[
    {
        "id": "0",
        "name": "hexagon",
        "region": {
            "origin": {
                "x": "157",
                "y": "161"
            },
            "size": {
                "width": "30",
                "height": "30"
            }
        }
    },
    {
        "id": "1",
        "name": "hexagon",
        "region": {
            "origin": {
                "x": "66",
                "y": "162"
            },
            "size": {
                "width": "32",
                "height": "32"
            }
        }
    },
    {
        "id": "2",
        "name": "triangle",
        "region": {
            "origin": {
                "x": "185",
                "y": "20"
            },
            "size": {
                "width": "30",
                "height": "40"
            }
        }
    },
    {
        "id": "3",
        "name": "hexagon",
        "region": {
            "origin": {
                "x": "73",
                "y": "66"
            },
            "size": {
                "width": "31",
                "height": "35"
            }
        }
    }
]