[
    {
        "id": "0",
        "name": "hexagon",
        "region": {
            "origin": {
                "x": "192",
                "y": "100"
            },
            "size": {
                "width": "28",
                "height": "36"
            }
        }
    },
    {
        "id": "1",
        "name": "hexagon",
        "region": {
            "origin": {
                "x": "145",
                "y": "147"
            },
            "size": {
                "width": "38",
                "height": "40"
            }
        }
    },
    {
        "id": "2",
        "name": "rhombus",
        "region": {
            "origin": {
                "x": "46",
                "y": "143"
            },
            "size": {
                "width": "29",
                "height": "29"
            }
        }
    },
    {
        "id": "3",
        "name": "hexagon",
        "region": {
            "origin": {
                "x": "46",
                "y": "57"
            },
            "size": {
                "width": "29",
                "height": "32"
            }
        }
    }
]