[
    {
        "id": "0",
        "name": "hexagon",
        "region": {
            "origin": {
                "x": "205",
                "y": "92"
            },
            "size": {
                "width": "29",
                "height": "32"
            }
        }
    },
    {
        "id": "1",
        "name": "triangle",
        "region": {
            "origin": {
                "x": "85",
                "y": "40"
            },
            "size": {
                "width": "30",
                "height": "29"
            }
        }
    },
    {
        "id": "2",
        "name": "circle",
        "region": {
            "origin": {
                "x": "148",
                "y": "176"
            },
            "size": {
                "width": "34",
                "height": "34"
            }
        }
    },
    {
        "id": "3",
        "name": "circle",
        "region": {
            "origin": {
                "x": "70",
                "y": "191"
            },
            "size": {
                "width": "34",
                "height": "34"
            }
        }
    },
    {
        "id": "4",
        "name": "circle",
        "region": {
            "origin": {
                "x": "94",
                "y": "129"
            },
            "size": {
                "width": "34",
                "height": "34"
            }
        }
    }
]