[
    {
        "id": "0",
        "name": "hexagon",
        "region": {
            "origin": {
                "x": "35",
                "y": "181"
            },
            "size": {
                "width": "38",
                "height": "39"
            }
        }
    },
    {
        "id": "1",
        "name": "circle",
        "region": {
            "origin": {
                "x": "149",
                "y": "174"
            },
            "size": {
                "width": "30",
                "height": "30"
            }
        }
    }
]