[
    {
        "id": "0",
        "name": "hexagon",
        "region": {
            "origin": {
                "x": "161",
                "y": "197"
            },
            "size": {
                "width": "36",
                "height": "37"
            }
        }
    },
    {
        "id": "1",
        "name": "hexagon",
        "region": {
            "origin": {
                "x": "90",
                "y": "40"
            },
            "size": {
                "width": "35",
                "height": "42"
            }
        }
    },
    {
        "id": "2",
        "name": "rhombus",
        "region": {
            "origin": {
                "x": "39",
                "y": "136"
            },
            "size": {
                "width": "33",
                "height": "33"
            }
        }
    }
]