[
    {
        "id": "0",
        "name": "hexagon",
        "region": {
            "origin": {
                "x": "182",
                "y": "152"
            },
            "size": {
                "width": "29",
                "height": "31"
            }
        }
    },
    {
        "id": "1",
        "name": "circle",
        "region": {
            "origin": {
                "x": "47",
                "y": "47"
            },
            "size": {
                "width": "30",
                "height": "30"
            }
        }
    },
    {
        "id": "2",
        "name": "triangle",
        "region": {
            "origin": {
                "x": "180",
                "y": "66"
            },
            "size": {
                "width": "31",
                "height": "40"
            }
        }
    }
]