[
    {
        "id": "0",
        "name": "hexagon",
        "region": {
            "origin": {
                "x": "43",
                "y": "182"
            },
            "size": {
                "width": "38",
                "height": "38"
            }
        }
    },
    {
        "id": "1",
        "name": "circle",
        "region": {
            "origin": {
                "x": "165",
                "y": "66"
            },
            "size": {
                "width": "30",
                "height": "30"
            }
        }
    },
    {
        "id": "2",
        "name": "rhombus",
        "region": {
            "origin": {
                "x": "77",
                "y": "69"
            },
            "size": {
                "width": "24",
                "height": "24"
            }
        }
    },
    {
        "id": "3",
        "name": "hexagon",
        "region": {
            "origin": {
                "x": "147",
                "y": "160"
            },
            "size": {
                "width": "33",
                "height": "37"
            }
        }
    }
]