[
    {
        "id": "0",
        "name": "hexagon",
        "region": {
            "origin": {
                "x": "172",
                "y": "45"
            },
            "size": {
                "width": "34",
                "height": "34"
            }
        }
    },
    {
        "id": "1",
        "name": "rhombus",
        "region": {
            "origin": {
                "x": "83",
                "y": "47"
            },
            "size": {
                "width": "33",
                "height": "33"
            }
        }
    },
    {
        "id": "2",
        "name": "rhombus",
        "region": {
            "origin": {
                "x": "14",
                "y": "141"
            },
            "size": {
                "width": "36",
                "height": "36"
            }
        }
    }
]