[
    {
        "id": "0",
        "name": "hexagon",
        "region": {
            "origin": {
                "x": "64",
                "y": "53"
            },
            "size": {
                "width": "29",
                "height": "36"
            }
        }
    },
    {
        "id": "1",
        "name": "hexagon",
        "region": {
            "origin": {
                "x": "200",
                "y": "104"
            },
            "size": {
                "width": "28",
                "height": "33"
            }
        }
    },
    {
        "id": "2",
        "name": "rhombus",
        "region": {
            "origin": {
                "x": "76",
                "y": "152"
            },
            "size": {
                "width": "24",
                "height": "24"
            }
        }
    }
]