[
    {
        "id": "0",
        "name": "hexagon",
        "region": {
            "origin": {
                "x": "213",
                "y": "74"
            },
            "size": {
                "width": "31",
                "height": "35"
            }
        }
    },
    {
        "id": "1",
        "name": "triangle",
        "region": {
            "origin": {
                "x": "80",
                "y": "157"
            },
            "size": {
                "width": "31",
                "height": "37"
            }
        }
    },
    {
        "id": "2",
        "name": "triangle",
        "region": {
            "origin": {
                "x": "188",
                "y": "142"
            },
            "size": {
                "width": "34",
                "height": "54"
            }
        }
    }
]